{
  "name": "H&W Kia",
  "base_url": "https://www.hwkia.com",
  "scraper_type": "sitemap",
  "api_platform": "sitemap_based",
  "filtering_rules": {
    "conditional_filters": {
      "location_filters": {
        "required_location": "H&W Kia"
      },
      "allowed_conditions": [
        "new",
        "used"
      ],
      "price_range": {
        "min": 8000,
        "max": 70000
      },
      "year_range": {
        "min": 2010,
        "max": 2024
      }
    },
    "validation_rules": {
      "required_fields": [
        "vin",
        "make",
        "model",
        "year"
      ],
      "field_types": {
        "price": "price",
        "year": "year",
        "mileage": "mileage"
      }
    }
  },
  "id": "hwkia",
  "created_at": "2025-07-18T23:02:20.357209",
  "updated_at": "2025-07-18T23:02:20.357210",
  "exact_replica": true,
  "original_patterns_preserved": 7,
  "generated_exact_replica_at": "2025-07-18T23:02:20.357198"
}