[
  {
    "vin": "MOCKPAPPA0000000000",
    "stock_number": "STK00000",
    "year": 2023,
    "make": "Toyota",
    "model": "Truck",
    "trim": "Premium",
    "price": 38899,
    "msrp": 68764,
    "mileage": 21316,
    "exterior_color": "Blue",
    "interior_color": "Black",
    "fuel_type": "Hybrid",
    "transmission": "Automatic",
    "condition": "certified",
    "url": "https://www.pappastoyota.com/inventory/0",
    "dealer_name": "Pappas Toyota",
    "scraped_at": "2025-07-24T02:46:54.678441"
  },
  {
    "vin": "MOCKPAPPA0000000001",
    "stock_number": "STK00001",
    "year": 2020,
    "make": "Toyota",
    "model": "Truck",
    "trim": "Base",
    "price": 52999,
    "msrp": 56027,
    "mileage": 33697,
    "exterior_color": "Black",
    "interior_color": "Tan",
    "fuel_type": "Hybrid",
    "transmission": "Manual",
    "condition": "new",
    "url": "https://www.pappastoyota.com/inventory/1",
    "dealer_name": "Pappas Toyota",
    "scraped_at": "2025-07-24T02:46:54.678469"
  },
  {
    "vin": "MOCKPAPPA0000000002",
    "stock_number": "STK00002",
    "year": 2025,
    "make": "Toyota",
    "model": "Convertible",
    "trim": "Limited",
    "price": 50281,
    "msrp": 47767,
    "mileage": 33968,
    "exterior_color": "White",
    "interior_color": "Tan",
    "fuel_type": "Hybrid",
    "transmission": "Manual",
    "condition": "new",
    "url": "https://www.pappastoyota.com/inventory/2",
    "dealer_name": "Pappas Toyota",
    "scraped_at": "2025-07-24T02:46:54.678489"
  },
  {
    "vin": "MOCKPAPPA0000000003",
    "stock_number": "STK00003",
    "year": 2025,
    "make": "Toyota",
    "model": "Sedan",
    "trim": "Sport",
    "price": 28888,
    "msrp": 78590,
    "mileage": 47096,
    "exterior_color": "Gray",
    "interior_color": "Gray",
    "fuel_type": "Hybrid",
    "transmission": "CVT",
    "condition": "new",
    "url": "https://www.pappastoyota.com/inventory/3",
    "dealer_name": "Pappas Toyota",
    "scraped_at": "2025-07-24T02:46:54.678509"
  },
  {
    "vin": "MOCKPAPPA0000000004",
    "stock_number": "STK00004",
    "year": 2021,
    "make": "Toyota",
    "model": "Truck",
    "trim": "Premium",
    "price": 67565,
    "msrp": 51881,
    "mileage": 31323,
    "exterior_color": "Red",
    "interior_color": "Tan",
    "fuel_type": "Gasoline",
    "transmission": "Automatic",
    "condition": "certified",
    "url": "https://www.pappastoyota.com/inventory/4",
    "dealer_name": "Pappas Toyota",
    "scraped_at": "2025-07-24T02:46:54.678530"
  },
  {
    "vin": "MOCKPAPPA0000000005",
    "stock_number": "STK00005",
    "year": 2023,
    "make": "Toyota",
    "model": "Coupe",
    "trim": "Limited",
    "price": 51150,
    "msrp": 36368,
    "mileage": 41248,
    "exterior_color": "Blue",
    "interior_color": "Tan",
    "fuel_type": "Gasoline",
    "transmission": "CVT",
    "condition": "used",
    "url": "https://www.pappastoyota.com/inventory/5",
    "dealer_name": "Pappas Toyota",
    "scraped_at": "2025-07-24T02:46:54.678550"
  },
  {
    "vin": "MOCKPAPPA0000000006",
    "stock_number": "STK00006",
    "year": 2025,
    "make": "Toyota",
    "model": "SUV",
    "trim": "Limited",
    "price": 51126,
    "msrp": 67304,
    "mileage": 12226,
    "exterior_color": "Silver",
    "interior_color": "Gray",
    "fuel_type": "Gasoline",
    "transmission": "Automatic",
    "condition": "used",
    "url": "https://www.pappastoyota.com/inventory/6",
    "dealer_name": "Pappas Toyota",
    "scraped_at": "2025-07-24T02:46:54.678571"
  },
  {
    "vin": "MOCKPAPPA0000000007",
    "stock_number": "STK00007",
    "year": 2021,
    "make": "Toyota",
    "model": "Truck",
    "trim": "Premium",
    "price": 50429,
    "msrp": 33630,
    "mileage": 563,
    "exterior_color": "Silver",
    "interior_color": "Tan",
    "fuel_type": "Electric",
    "transmission": "Manual",
    "condition": "new",
    "url": "https://www.pappastoyota.com/inventory/7",
    "dealer_name": "Pappas Toyota",
    "scraped_at": "2025-07-24T02:46:54.678590"
  },
  {
    "vin": "MOCKPAPPA0000000008",
    "stock_number": "STK00008",
    "year": 2023,
    "make": "Toyota",
    "model": "Truck",
    "trim": "Limited",
    "price": 29948,
    "msrp": 73191,
    "mileage": 34244,
    "exterior_color": "Gray",
    "interior_color": "Black",
    "fuel_type": "Electric",
    "transmission": "CVT",
    "condition": "used",
    "url": "https://www.pappastoyota.com/inventory/8",
    "dealer_name": "Pappas Toyota",
    "scraped_at": "2025-07-24T02:46:54.678610"
  },
  {
    "vin": "MOCKPAPPA0000000009",
    "stock_number": "STK00009",
    "year": 2023,
    "make": "Toyota",
    "model": "Truck",
    "trim": "Base",
    "price": 37436,
    "msrp": 55399,
    "mileage": 28464,
    "exterior_color": "Red",
    "interior_color": "Tan",
    "fuel_type": "Gasoline",
    "transmission": "Automatic",
    "condition": "new",
    "url": "https://www.pappastoyota.com/inventory/9",
    "dealer_name": "Pappas Toyota",
    "scraped_at": "2025-07-24T02:46:54.678629"
  },
  {
    "vin": "MOCKPAPPA0000000010",
    "stock_number": "STK00010",
    "year": 2024,
    "make": "Toyota",
    "model": "Coupe",
    "trim": "Premium",
    "price": 78575,
    "msrp": 84487,
    "mileage": 21254,
    "exterior_color": "Silver",
    "interior_color": "Black",
    "fuel_type": "Hybrid",
    "transmission": "CVT",
    "condition": "certified",
    "url": "https://www.pappastoyota.com/inventory/10",
    "dealer_name": "Pappas Toyota",
    "scraped_at": "2025-07-24T02:46:54.678649"
  },
  {
    "vin": "MOCKPAPPA0000000011",
    "stock_number": "STK00011",
    "year": 2023,
    "make": "Toyota",
    "model": "Convertible",
    "trim": "Premium",
    "price": 39912,
    "msrp": 50136,
    "mileage": 12380,
    "exterior_color": "Black",
    "interior_color": "Gray",
    "fuel_type": "Gasoline",
    "transmission": "Automatic",
    "condition": "certified",
    "url": "https://www.pappastoyota.com/inventory/11",
    "dealer_name": "Pappas Toyota",
    "scraped_at": "2025-07-24T02:46:54.678668"
  },
  {
    "vin": "MOCKPAPPA0000000012",
    "stock_number": "STK00012",
    "year": 2025,
    "make": "Toyota",
    "model": "Sedan",
    "trim": "Base",
    "price": 62261,
    "msrp": 59135,
    "mileage": 28154,
    "exterior_color": "Red",
    "interior_color": "Gray",
    "fuel_type": "Hybrid",
    "transmission": "CVT",
    "condition": "new",
    "url": "https://www.pappastoyota.com/inventory/12",
    "dealer_name": "Pappas Toyota",
    "scraped_at": "2025-07-24T02:46:54.678688"
  },
  {
    "vin": "MOCKPAPPA0000000013",
    "stock_number": "STK00013",
    "year": 2024,
    "make": "Toyota",
    "model": "SUV",
    "trim": "Limited",
    "price": 74059,
    "msrp": 31459,
    "mileage": 21550,
    "exterior_color": "Black",
    "interior_color": "Black",
    "fuel_type": "Gasoline",
    "transmission": "Manual",
    "condition": "new",
    "url": "https://www.pappastoyota.com/inventory/13",
    "dealer_name": "Pappas Toyota",
    "scraped_at": "2025-07-24T02:46:54.678707"
  },
  {
    "vin": "MOCKPAPPA0000000014",
    "stock_number": "STK00014",
    "year": 2021,
    "make": "Toyota",
    "model": "Convertible",
    "trim": "Base",
    "price": 55630,
    "msrp": 83345,
    "mileage": 42717,
    "exterior_color": "Red",
    "interior_color": "Tan",
    "fuel_type": "Electric",
    "transmission": "CVT",
    "condition": "new",
    "url": "https://www.pappastoyota.com/inventory/14",
    "dealer_name": "Pappas Toyota",
    "scraped_at": "2025-07-24T02:46:54.678734"
  },
  {
    "vin": "MOCKPAPPA0000000015",
    "stock_number": "STK00015",
    "year": 2020,
    "make": "Toyota",
    "model": "SUV",
    "trim": "Base",
    "price": 32516,
    "msrp": 82981,
    "mileage": 16292,
    "exterior_color": "Gray",
    "interior_color": "Black",
    "fuel_type": "Electric",
    "transmission": "Manual",
    "condition": "new",
    "url": "https://www.pappastoyota.com/inventory/15",
    "dealer_name": "Pappas Toyota",
    "scraped_at": "2025-07-24T02:46:54.678754"
  },
  {
    "vin": "MOCKPAPPA0000000016",
    "stock_number": "STK00016",
    "year": 2021,
    "make": "Toyota",
    "model": "Convertible",
    "trim": "Limited",
    "price": 53080,
    "msrp": 61515,
    "mileage": 825,
    "exterior_color": "Silver",
    "interior_color": "Gray",
    "fuel_type": "Gasoline",
    "transmission": "CVT",
    "condition": "used",
    "url": "https://www.pappastoyota.com/inventory/16",
    "dealer_name": "Pappas Toyota",
    "scraped_at": "2025-07-24T02:46:54.678774"
  },
  {
    "vin": "MOCKPAPPA0000000017",
    "stock_number": "STK00017",
    "year": 2023,
    "make": "Toyota",
    "model": "Truck",
    "trim": "Limited",
    "price": 34668,
    "msrp": 73488,
    "mileage": 23259,
    "exterior_color": "Black",
    "interior_color": "Gray",
    "fuel_type": "Hybrid",
    "transmission": "CVT",
    "condition": "used",
    "url": "https://www.pappastoyota.com/inventory/17",
    "dealer_name": "Pappas Toyota",
    "scraped_at": "2025-07-24T02:46:54.678793"
  },
  {
    "vin": "MOCKPAPPA0000000018",
    "stock_number": "STK00018",
    "year": 2023,
    "make": "Toyota",
    "model": "Sedan",
    "trim": "Base",
    "price": 57047,
    "msrp": 40925,
    "mileage": 17169,
    "exterior_color": "Red",
    "interior_color": "Gray",
    "fuel_type": "Hybrid",
    "transmission": "Manual",
    "condition": "used",
    "url": "https://www.pappastoyota.com/inventory/18",
    "dealer_name": "Pappas Toyota",
    "scraped_at": "2025-07-24T02:46:54.678812"
  },
  {
    "vin": "MOCKPAPPA0000000019",
    "stock_number": "STK00019",
    "year": 2025,
    "make": "Toyota",
    "model": "Truck",
    "trim": "Limited",
    "price": 34636,
    "msrp": 54306,
    "mileage": 49828,
    "exterior_color": "Red",
    "interior_color": "Tan",
    "fuel_type": "Gasoline",
    "transmission": "CVT",
    "condition": "certified",
    "url": "https://www.pappastoyota.com/inventory/19",
    "dealer_name": "Pappas Toyota",
    "scraped_at": "2025-07-24T02:46:54.678832"
  },
  {
    "vin": "MOCKPAPPA0000000020",
    "stock_number": "STK00020",
    "year": 2021,
    "make": "Toyota",
    "model": "Convertible",
    "trim": "Limited",
    "price": 43406,
    "msrp": 40703,
    "mileage": 8818,
    "exterior_color": "Black",
    "interior_color": "Gray",
    "fuel_type": "Electric",
    "transmission": "Automatic",
    "condition": "new",
    "url": "https://www.pappastoyota.com/inventory/20",
    "dealer_name": "Pappas Toyota",
    "scraped_at": "2025-07-24T02:46:54.678853"
  },
  {
    "vin": "MOCKPAPPA0000000021",
    "stock_number": "STK00021",
    "year": 2021,
    "make": "Toyota",
    "model": "SUV",
    "trim": "Premium",
    "price": 49230,
    "msrp": 76156,
    "mileage": 38639,
    "exterior_color": "Red",
    "interior_color": "Gray",
    "fuel_type": "Hybrid",
    "transmission": "Manual",
    "condition": "new",
    "url": "https://www.pappastoyota.com/inventory/21",
    "dealer_name": "Pappas Toyota",
    "scraped_at": "2025-07-24T02:46:54.678872"
  },
  {
    "vin": "MOCKPAPPA0000000022",
    "stock_number": "STK00022",
    "year": 2021,
    "make": "Toyota",
    "model": "Convertible",
    "trim": "Base",
    "price": 41934,
    "msrp": 55344,
    "mileage": 17452,
    "exterior_color": "White",
    "interior_color": "Gray",
    "fuel_type": "Hybrid",
    "transmission": "Manual",
    "condition": "certified",
    "url": "https://www.pappastoyota.com/inventory/22",
    "dealer_name": "Pappas Toyota",
    "scraped_at": "2025-07-24T02:46:54.678892"
  },
  {
    "vin": "MOCKPAPPA0000000023",
    "stock_number": "STK00023",
    "year": 2024,
    "make": "Toyota",
    "model": "Convertible",
    "trim": "Premium",
    "price": 53105,
    "msrp": 78350,
    "mileage": 46802,
    "exterior_color": "Silver",
    "interior_color": "Gray",
    "fuel_type": "Electric",
    "transmission": "Manual",
    "condition": "used",
    "url": "https://www.pappastoyota.com/inventory/23",
    "dealer_name": "Pappas Toyota",
    "scraped_at": "2025-07-24T02:46:54.678911"
  },
  {
    "vin": "MOCKPAPPA0000000024",
    "stock_number": "STK00024",
    "year": 2021,
    "make": "Toyota",
    "model": "Sedan",
    "trim": "Base",
    "price": 41146,
    "msrp": 44879,
    "mileage": 37603,
    "exterior_color": "Blue",
    "interior_color": "Gray",
    "fuel_type": "Hybrid",
    "transmission": "Automatic",
    "condition": "new",
    "url": "https://www.pappastoyota.com/inventory/24",
    "dealer_name": "Pappas Toyota",
    "scraped_at": "2025-07-24T02:46:54.678931"
  },
  {
    "vin": "MOCKPAPPA0000000025",
    "stock_number": "STK00025",
    "year": 2020,
    "make": "Toyota",
    "model": "Convertible",
    "trim": "Premium",
    "price": 43912,
    "msrp": 65232,
    "mileage": 10735,
    "exterior_color": "White",
    "interior_color": "Tan",
    "fuel_type": "Gasoline",
    "transmission": "CVT",
    "condition": "new",
    "url": "https://www.pappastoyota.com/inventory/25",
    "dealer_name": "Pappas Toyota",
    "scraped_at": "2025-07-24T02:46:54.678950"
  },
  {
    "vin": "MOCKPAPPA0000000026",
    "stock_number": "STK00026",
    "year": 2025,
    "make": "Toyota",
    "model": "Sedan",
    "trim": "Base",
    "price": 74241,
    "msrp": 73943,
    "mileage": 20730,
    "exterior_color": "Red",
    "interior_color": "Gray",
    "fuel_type": "Gasoline",
    "transmission": "Automatic",
    "condition": "used",
    "url": "https://www.pappastoyota.com/inventory/26",
    "dealer_name": "Pappas Toyota",
    "scraped_at": "2025-07-24T02:46:54.678969"
  },
  {
    "vin": "MOCKPAPPA0000000027",
    "stock_number": "STK00027",
    "year": 2025,
    "make": "Toyota",
    "model": "SUV",
    "trim": "Premium",
    "price": 56528,
    "msrp": 35314,
    "mileage": 15083,
    "exterior_color": "White",
    "interior_color": "Gray",
    "fuel_type": "Hybrid",
    "transmission": "Automatic",
    "condition": "used",
    "url": "https://www.pappastoyota.com/inventory/27",
    "dealer_name": "Pappas Toyota",
    "scraped_at": "2025-07-24T02:46:54.678989"
  },
  {
    "vin": "MOCKPAPPA0000000028",
    "stock_number": "STK00028",
    "year": 2020,
    "make": "Toyota",
    "model": "Convertible",
    "trim": "Premium",
    "price": 75244,
    "msrp": 43403,
    "mileage": 4834,
    "exterior_color": "Blue",
    "interior_color": "Black",
    "fuel_type": "Hybrid",
    "transmission": "CVT",
    "condition": "used",
    "url": "https://www.pappastoyota.com/inventory/28",
    "dealer_name": "Pappas Toyota",
    "scraped_at": "2025-07-24T02:46:54.679008"
  },
  {
    "vin": "MOCKPAPPA0000000029",
    "stock_number": "STK00029",
    "year": 2025,
    "make": "Toyota",
    "model": "Truck",
    "trim": "Base",
    "price": 25185,
    "msrp": 55500,
    "mileage": 10594,
    "exterior_color": "Blue",
    "interior_color": "Gray",
    "fuel_type": "Electric",
    "transmission": "CVT",
    "condition": "used",
    "url": "https://www.pappastoyota.com/inventory/29",
    "dealer_name": "Pappas Toyota",
    "scraped_at": "2025-07-24T02:46:54.679027"
  }
]